Metadata-Version: 1.0
Name: distributions-tyagi
Version: 0.1
Summary: Gaussian distributions
Home-page: UNKNOWN
Author: Sarthak Tyagi
Author-email: thesarthaktyagi@gmail.com
License: UNKNOWN
Platform: UNKNOWN
